smtp_emailer/__init__.py
smtp_emailer-6.0.0.dist-info/METADATA
smtp_emailer-6.0.0.dist-info/WHEEL
smtp_emailer-6.0.0.dist-info/licenses/LICENSE
smtp_emailer-6.0.0.dist-info/RECORD
