Metadata-Version: 2.3
Name: smtp-emailer
Version: 6.0.0
Summary: Simple utility for sending emails via SMTP.
Project-URL: Homepage, https://github.com/mizuki-hikaru/smtp-emailer
Project-URL: Issues, https://github.com/mizuki-hikaru/smtp-emailer/issues
Author-email: Mizuki Hikaru <mizuki@hikaru.org>
License-File: LICENSE
Classifier: License :: OSI Approved :: MIT License
Classifier: Operating System :: OS Independent
Classifier: Programming Language :: Python :: 3
Requires-Python: >=3.9
